Workbook

Sheet Settings
A2: ⚙ ENGINEER & CONTRACTOR TIER PROGRAM — SETTINGS
A3: Two independent tiers per member: DISCOUNT tier and POINTS tier. Both reviewed annually based on total sale value. Members locked at their tier all year — upgrade or downgrade applies the following year.
A5: Parameter | B5: Gold 🥇 | C5: Platinum 💎 | D5: Diamond 👑 | E5: Notes
A7: A. DISCOUNT TIER (qualified by annual sale value)
A8: Tier name | B8: Gold | C8: Platinum | D8: Diamond | E8: Display label
A9: Annual sale value threshold (₹) | B9: 1000000 | C9: 3000000 | D9: 5000000 | E9: Total invoice value during the year required to hold/upgrade to this tier next year
A10: Discount rate | B10: 0.08 | C10: 0.1 | D10: 0.12 | E10: Default discount on invoices. Per-purchase override is handled in the software.
A12: B. POINTS TIER (qualified by annual sale value, separate from discount tier)
A13: Tier name | B13: Gold | C13: Platinum | D13: Diamond | E13: Display label
A14: Annual sale value threshold (₹) | B14: 3000000 | C14: 7000000 | D14: 7100000
A15: Points multiplier | B15: 1 | C15: 1.5 | D15: 2 | E15: Multiplier applied to base earn rate
A16: Base earn rate (pts per ₹1,000) | B16: 1 | E16: Same for all tiers; the points multiplier scales it per tier
A17: Effective earn rate (pts/₹1,000) | B17: =$B$16*B15 -> 1 | C17: =$B$16*C15 -> 1.5 | D17: =$B$16*D15 -> 2 | E17: Calculated
A19: C. ANNUAL REVIEW LOGIC
A20: Upgrade rule | B20: If annual sale value ≥ next-tier threshold → upgrade next year
A21: Hold rule | B21: If annual sale value ≥ current-tier threshold → keep current tier next year
A22: Downgrade rule | B22: If annual sale value < current-tier threshold → drop one tier next year (Diamond→Platinum, Platinum→Gold, Gold→stays Gold)
A23: Mid-year | B23: Tier is locked. No mid-year upgrades or downgrades. Discount and points multiplier both stay at start-of-year tier.
A25: D. POINTS-TO-CURRENCY CONVERSION
A26: Points-to-₹ conversion (₹ per point) | B26: 1 | C26: 1.25 | D26: 1.7 | E26: Cash value of 1 point when redeemed at this points tier
A28: E. BONUS POINTS (cumulative-points milestones)
A29: Crossing a points threshold awards a one-time lump-sum AND boosts multiplier on future invoices
B30: Bonus 1 | C30: Bonus 2 | D30: Bonus 3
A31: Cumulative-points threshold | B31: 2000 | C31: 5000 | D31: 10000
A32: Multiplier boost (stacks on tier mult.) | B32: 0.05 | C32: 0.1 | D32: 0.15
A33: Flat bonus points awarded (lump sum) | B33: 100 | C33: 200 | D33: 300
A34: Boost applies only to invoices AFTER threshold is crossed (not retroactive)
A35: Points resets every year

Sheet Bill Calculator
A2: 🧮 ENGINEER / CONTRACTOR — BILL CALCULATOR (single year)
A3: Member's tiers are locked all year. Enter starting Discount tier and starting Points tier. Year-end totals determine next year's tiers (upgrade if hit next-tier threshold, hold if hit current threshold, drop one step otherwise).
A5: Member name: | D5: Starting Discount tier: | E5: Gold | G5: Starting Points tier: | H5: Gold
D6: Discount rate this year: | E6: =IF(E5="Diamond",Settings!D10,IF(E5="Platinum",Settings!C10,Settings!B10)) -> 0.08 | G6: Points multiplier this year: | H6: =IF(H5="Diamond",Settings!D15,IF(H5="Platinum",Settings!C15,Settings!B15)) -> 1
A8: # | B8: Project / Description | C8: Invoice value (₹) | D8: Discount (₹) | E8: Net invoice (₹) | F8: Pts earned (base) | G8: Cum. pts before | H8: Bonus boost rate | I8: Lump-sum bonus | J8: Total pts (row)
A9: 1
A10: 2
A11: 3
A12: 4
A13: 5
A14: 6 | C14: 7000000 | D14: =IF(C14="","",C14*$E$6) -> 560000 | E14: =IF(C14="","",C14-D14) -> 6440000 | F14: =IF(C14="","",(C14/1000*Settings!$B$16*$H$6)+MAX(0,MIN(G14+(C14/1000*Settings!$B$16*$H$6),Settings!$C$31)-MAX(G14,Settings!$B$31))*Settings!$B$32+MAX(0,MIN(G14+(C14/1000*Settings!$B$16*$H$6),Settings!$D$31)-MAX(G14,Settings!$C$31))*Settings!$C$32+MAX(0,(G14+(C14/1000*Settings!$B$16*$H$6))-MAX(G14,Settings!$D$31))*Settings!$D$32) -> 7350 | G14: =IF(C14="","",SUM($J$9:J13)) -> 0 | H14: =IF(OR(C14="",C14=0),"",(F14-(C14/1000*Settings!$B$16*$H$6))/(C14/1000*Settings!$B$16*$H$6)) -> 0.05 | I14: =IF(C14="","",IF(AND(G14<Settings!$B$31,(G14+F14)>=Settings!$B$31),Settings!$B$33,0)+IF(AND(G14<Settings!$C$31,(G14+F14)>=Settings!$C$31),Settings!$C$33,0)+IF(AND(G14<Settings!$D$31,(G14+F14)>=Settings!$D$31),Settings!$D$33,0)) -> 300 | J14: =IF(C14="","",F14+I14) -> 7650
A15: 7 | D15: =IF(C15="","",C15*$E$6) | E15: =IF(C15="","",C15-D15) | F15: =IF(C15="","",(C15/1000*Settings!$B$16*$H$6)+MAX(0,MIN(G15+(C15/1000*Settings!$B$16*$H$6),Settings!$C$31)-MAX(G15,Settings!$B$31))*Settings!$B$32+MAX(0,MIN(G15+(C15/1000*Settings!$B$16*$H$6),Settings!$D$31)-MAX(G15,Settings!$C$31))*Settings!$C$32+MAX(0,(G15+(C15/1000*Settings!$B$16*$H$6))-MAX(G15,Settings!$D$31))*Settings!$D$32) | G15: =IF(C15="","",SUM($J$9:J14)) | H15: =IF(OR(C15="",C15=0),"",(F15-(C15/1000*Settings!$B$16*$H$6))/(C15/1000*Settings!$B$16*$H$6)) | I15: =IF(C15="","",IF(AND(G15<Settings!$B$31,(G15+F15)>=Settings!$B$31),Settings!$B$33,0)+IF(AND(G15<Settings!$C$31,(G15+F15)>=Settings!$C$31),Settings!$C$33,0)+IF(AND(G15<Settings!$D$31,(G15+F15)>=Settings!$D$31),Settings!$D$33,0)) | J15: =IF(C15="","",F15+I15)
A16: 8 | D16: =IF(C16="","",C16*$E$6) | E16: =IF(C16="","",C16-D16) | F16: =IF(C16="","",(C16/1000*Settings!$B$16*$H$6)+MAX(0,MIN(G16+(C16/1000*Settings!$B$16*$H$6),Settings!$C$31)-MAX(G16,Settings!$B$31))*Settings!$B$32+MAX(0,MIN(G16+(C16/1000*Settings!$B$16*$H$6),Settings!$D$31)-MAX(G16,Settings!$C$31))*Settings!$C$32+MAX(0,(G16+(C16/1000*Settings!$B$16*$H$6))-MAX(G16,Settings!$D$31))*Settings!$D$32) | G16: =IF(C16="","",SUM($J$9:J15)) | H16: =IF(OR(C16="",C16=0),"",(F16-(C16/1000*Settings!$B$16*$H$6))/(C16/1000*Settings!$B$16*$H$6)) | I16: =IF(C16="","",IF(AND(G16<Settings!$B$31,(G16+F16)>=Settings!$B$31),Settings!$B$33,0)+IF(AND(G16<Settings!$C$31,(G16+F16)>=Settings!$C$31),Settings!$C$33,0)+IF(AND(G16<Settings!$D$31,(G16+F16)>=Settings!$D$31),Settings!$D$33,0)) | J16: =IF(C16="","",F16+I16)
A17: 9 | D17: =IF(C17="","",C17*$E$6) | E17: =IF(C17="","",C17-D17) | F17: =IF(C17="","",(C17/1000*Settings!$B$16*$H$6)+MAX(0,MIN(G17+(C17/1000*Settings!$B$16*$H$6),Settings!$C$31)-MAX(G17,Settings!$B$31))*Settings!$B$32+MAX(0,MIN(G17+(C17/1000*Settings!$B$16*$H$6),Settings!$D$31)-MAX(G17,Settings!$C$31))*Settings!$C$32+MAX(0,(G17+(C17/1000*Settings!$B$16*$H$6))-MAX(G17,Settings!$D$31))*Settings!$D$32) | G17: =IF(C17="","",SUM($J$9:J16)) | H17: =IF(OR(C17="",C17=0),"",(F17-(C17/1000*Settings!$B$16*$H$6))/(C17/1000*Settings!$B$16*$H$6)) | I17: =IF(C17="","",IF(AND(G17<Settings!$B$31,(G17+F17)>=Settings!$B$31),Settings!$B$33,0)+IF(AND(G17<Settings!$C$31,(G17+F17)>=Settings!$C$31),Settings!$C$33,0)+IF(AND(G17<Settings!$D$31,(G17+F17)>=Settings!$D$31),Settings!$D$33,0)) | J17: =IF(C17="","",F17+I17)
A18: 10 | D18: =IF(C18="","",C18*$E$6) | E18: =IF(C18="","",C18-D18) | F18: =IF(C18="","",(C18/1000*Settings!$B$16*$H$6)+MAX(0,MIN(G18+(C18/1000*Settings!$B$16*$H$6),Settings!$C$31)-MAX(G18,Settings!$B$31))*Settings!$B$32+MAX(0,MIN(G18+(C18/1000*Settings!$B$16*$H$6),Settings!$D$31)-MAX(G18,Settings!$C$31))*Settings!$C$32+MAX(0,(G18+(C18/1000*Settings!$B$16*$H$6))-MAX(G18,Settings!$D$31))*Settings!$D$32) | G18: =IF(C18="","",SUM($J$9:J17)) | H18: =IF(OR(C18="",C18=0),"",(F18-(C18/1000*Settings!$B$16*$H$6))/(C18/1000*Settings!$B$16*$H$6)) | I18: =IF(C18="","",IF(AND(G18<Settings!$B$31,(G18+F18)>=Settings!$B$31),Settings!$B$33,0)+IF(AND(G18<Settings!$C$31,(G18+F18)>=Settings!$C$31),Settings!$C$33,0)+IF(AND(G18<Settings!$D$31,(G18+F18)>=Settings!$D$31),Settings!$D$33,0)) | J18: =IF(C18="","",F18+I18)
A19: 11 | D19: =IF(C19="","",C19*$E$6) | E19: =IF(C19="","",C19-D19) | F19: =IF(C19="","",(C19/1000*Settings!$B$16*$H$6)+MAX(0,MIN(G19+(C19/1000*Settings!$B$16*$H$6),Settings!$C$31)-MAX(G19,Settings!$B$31))*Settings!$B$32+MAX(0,MIN(G19+(C19/1000*Settings!$B$16*$H$6),Settings!$D$31)-MAX(G19,Settings!$C$31))*Settings!$C$32+MAX(0,(G19+(C19/1000*Settings!$B$16*$H$6))-MAX(G19,Settings!$D$31))*Settings!$D$32) | G19: =IF(C19="","",SUM($J$9:J18)) | H19: =IF(OR(C19="",C19=0),"",(F19-(C19/1000*Settings!$B$16*$H$6))/(C19/1000*Settings!$B$16*$H$6)) | I19: =IF(C19="","",IF(AND(G19<Settings!$B$31,(G19+F19)>=Settings!$B$31),Settings!$B$33,0)+IF(AND(G19<Settings!$C$31,(G19+F19)>=Settings!$C$31),Settings!$C$33,0)+IF(AND(G19<Settings!$D$31,(G19+F19)>=Settings!$D$31),Settings!$D$33,0)) | J19: =IF(C19="","",F19+I19)
A20: 12 | D20: =IF(C20="","",C20*$E$6) | E20: =IF(C20="","",C20-D20) | F20: =IF(C20="","",(C20/1000*Settings!$B$16*$H$6)+MAX(0,MIN(G20+(C20/1000*Settings!$B$16*$H$6),Settings!$C$31)-MAX(G20,Settings!$B$31))*Settings!$B$32+MAX(0,MIN(G20+(C20/1000*Settings!$B$16*$H$6),Settings!$D$31)-MAX(G20,Settings!$C$31))*Settings!$C$32+MAX(0,(G20+(C20/1000*Settings!$B$16*$H$6))-MAX(G20,Settings!$D$31))*Settings!$D$32) | G20: =IF(C20="","",SUM($J$9:J19)) | H20: =IF(OR(C20="",C20=0),"",(F20-(C20/1000*Settings!$B$16*$H$6))/(C20/1000*Settings!$B$16*$H$6)) | I20: =IF(C20="","",IF(AND(G20<Settings!$B$31,(G20+F20)>=Settings!$B$31),Settings!$B$33,0)+IF(AND(G20<Settings!$C$31,(G20+F20)>=Settings!$C$31),Settings!$C$33,0)+IF(AND(G20<Settings!$D$31,(G20+F20)>=Settings!$D$31),Settings!$D$33,0)) | J20: =IF(C20="","",F20+I20)
A21: 13 | D21: =IF(C21="","",C21*$E$6) | E21: =IF(C21="","",C21-D21) | F21: =IF(C21="","",(C21/1000*Settings!$B$16*$H$6)+MAX(0,MIN(G21+(C21/1000*Settings!$B$16*$H$6),Settings!$C$31)-MAX(G21,Settings!$B$31))*Settings!$B$32+MAX(0,MIN(G21+(C21/1000*Settings!$B$16*$H$6),Settings!$D$31)-MAX(G21,Settings!$C$31))*Settings!$C$32+MAX(0,(G21+(C21/1000*Settings!$B$16*$H$6))-MAX(G21,Settings!$D$31))*Settings!$D$32) | G21: =IF(C21="","",SUM($J$9:J20)) | H21: =IF(OR(C21="",C21=0),"",(F21-(C21/1000*Settings!$B$16*$H$6))/(C21/1000*Settings!$B$16*$H$6)) | I21: =IF(C21="","",IF(AND(G21<Settings!$B$31,(G21+F21)>=Settings!$B$31),Settings!$B$33,0)+IF(AND(G21<Settings!$C$31,(G21+F21)>=Settings!$C$31),Settings!$C$33,0)+IF(AND(G21<Settings!$D$31,(G21+F21)>=Settings!$D$31),Settings!$D$33,0)) | J21: =IF(C21="","",F21+I21)
A22: 14 | D22: =IF(C22="","",C22*$E$6) | E22: =IF(C22="","",C22-D22) | F22: =IF(C22="","",(C22/1000*Settings!$B$16*$H$6)+MAX(0,MIN(G22+(C22/1000*Settings!$B$16*$H$6),Settings!$C$31)-MAX(G22,Settings!$B$31))*Settings!$B$32+MAX(0,MIN(G22+(C22/1000*Settings!$B$16*$H$6),Settings!$D$31)-MAX(G22,Settings!$C$31))*Settings!$C$32+MAX(0,(G22+(C22/1000*Settings!$B$16*$H$6))-MAX(G22,Settings!$D$31))*Settings!$D$32) | G22: =IF(C22="","",SUM($J$9:J21)) | H22: =IF(OR(C22="",C22=0),"",(F22-(C22/1000*Settings!$B$16*$H$6))/(C22/1000*Settings!$B$16*$H$6)) | I22: =IF(C22="","",IF(AND(G22<Settings!$B$31,(G22+F22)>=Settings!$B$31),Settings!$B$33,0)+IF(AND(G22<Settings!$C$31,(G22+F22)>=Settings!$C$31),Settings!$C$33,0)+IF(AND(G22<Settings!$D$31,(G22+F22)>=Settings!$D$31),Settings!$D$33,0)) | J22: =IF(C22="","",F22+I22)
A23: 15 | D23: =IF(C23="","",C23*$E$6) | E23: =IF(C23="","",C23-D23) | F23: =IF(C23="","",(C23/1000*Settings!$B$16*$H$6)+MAX(0,MIN(G23+(C23/1000*Settings!$B$16*$H$6),Settings!$C$31)-MAX(G23,Settings!$B$31))*Settings!$B$32+MAX(0,MIN(G23+(C23/1000*Settings!$B$16*$H$6),Settings!$D$31)-MAX(G23,Settings!$C$31))*Settings!$C$32+MAX(0,(G23+(C23/1000*Settings!$B$16*$H$6))-MAX(G23,Settings!$D$31))*Settings!$D$32) | G23: =IF(C23="","",SUM($J$9:J22)) | H23: =IF(OR(C23="",C23=0),"",(F23-(C23/1000*Settings!$B$16*$H$6))/(C23/1000*Settings!$B$16*$H$6)) | I23: =IF(C23="","",IF(AND(G23<Settings!$B$31,(G23+F23)>=Settings!$B$31),Settings!$B$33,0)+IF(AND(G23<Settings!$C$31,(G23+F23)>=Settings!$C$31),Settings!$C$33,0)+IF(AND(G23<Settings!$D$31,(G23+F23)>=Settings!$D$31),Settings!$D$33,0)) | J23: =IF(C23="","",F23+I23)
A24: 16 | D24: =IF(C24="","",C24*$E$6) | E24: =IF(C24="","",C24-D24) | F24: =IF(C24="","",(C24/1000*Settings!$B$16*$H$6)+MAX(0,MIN(G24+(C24/1000*Settings!$B$16*$H$6),Settings!$C$31)-MAX(G24,Settings!$B$31))*Settings!$B$32+MAX(0,MIN(G24+(C24/1000*Settings!$B$16*$H$6),Settings!$D$31)-MAX(G24,Settings!$C$31))*Settings!$C$32+MAX(0,(G24+(C24/1000*Settings!$B$16*$H$6))-MAX(G24,Settings!$D$31))*Settings!$D$32) | G24: =IF(C24="","",SUM($J$9:J23)) | H24: =IF(OR(C24="",C24=0),"",(F24-(C24/1000*Settings!$B$16*$H$6))/(C24/1000*Settings!$B$16*$H$6)) | I24: =IF(C24="","",IF(AND(G24<Settings!$B$31,(G24+F24)>=Settings!$B$31),Settings!$B$33,0)+IF(AND(G24<Settings!$C$31,(G24+F24)>=Settings!$C$31),Settings!$C$33,0)+IF(AND(G24<Settings!$D$31,(G24+F24)>=Settings!$D$31),Settings!$D$33,0)) | J24: =IF(C24="","",F24+I24)
A25: 17 | D25: =IF(C25="","",C25*$E$6) | E25: =IF(C25="","",C25-D25) | F25: =IF(C25="","",(C25/1000*Settings!$B$16*$H$6)+MAX(0,MIN(G25+(C25/1000*Settings!$B$16*$H$6),Settings!$C$31)-MAX(G25,Settings!$B$31))*Settings!$B$32+MAX(0,MIN(G25+(C25/1000*Settings!$B$16*$H$6),Settings!$D$31)-MAX(G25,Settings!$C$31))*Settings!$C$32+MAX(0,(G25+(C25/1000*Settings!$B$16*$H$6))-MAX(G25,Settings!$D$31))*Settings!$D$32) | G25: =IF(C25="","",SUM($J$9:J24)) | H25: =IF(OR(C25="",C25=0),"",(F25-(C25/1000*Settings!$B$16*$H$6))/(C25/1000*Settings!$B$16*$H$6)) | I25: =IF(C25="","",IF(AND(G25<Settings!$B$31,(G25+F25)>=Settings!$B$31),Settings!$B$33,0)+IF(AND(G25<Settings!$C$31,(G25+F25)>=Settings!$C$31),Settings!$C$33,0)+IF(AND(G25<Settings!$D$31,(G25+F25)>=Settings!$D$31),Settings!$D$33,0)) | J25: =IF(C25="","",F25+I25)
A26: 18 | D26: =IF(C26="","",C26*$E$6) | E26: =IF(C26="","",C26-D26) | F26: =IF(C26="","",(C26/1000*Settings!$B$16*$H$6)+MAX(0,MIN(G26+(C26/1000*Settings!$B$16*$H$6),Settings!$C$31)-MAX(G26,Settings!$B$31))*Settings!$B$32+MAX(0,MIN(G26+(C26/1000*Settings!$B$16*$H$6),Settings!$D$31)-MAX(G26,Settings!$C$31))*Settings!$C$32+MAX(0,(G26+(C26/1000*Settings!$B$16*$H$6))-MAX(G26,Settings!$D$31))*Settings!$D$32) | G26: =IF(C26="","",SUM($J$9:J25)) | H26: =IF(OR(C26="",C26=0),"",(F26-(C26/1000*Settings!$B$16*$H$6))/(C26/1000*Settings!$B$16*$H$6)) | I26: =IF(C26="","",IF(AND(G26<Settings!$B$31,(G26+F26)>=Settings!$B$31),Settings!$B$33,0)+IF(AND(G26<Settings!$C$31,(G26+F26)>=Settings!$C$31),Settings!$C$33,0)+IF(AND(G26<Settings!$D$31,(G26+F26)>=Settings!$D$31),Settings!$D$33,0)) | J26: =IF(C26="","",F26+I26)
... A58: 50 | D58: =IF(C58="","",C58*$E$6) | E58: =IF(C58="","",C58-D58) | F58: =IF(C58="","",(C58/1000*Settings!$B$16*$H$6)+MAX(0,MIN(G58+(C58/1000*Settings!$B$16*$H$6),Settings!$C$31)-MAX(G58,Settings!$B$31))*Settings!$B$32+MAX(0,MIN(G58+(C58/1000*Settings!$B$16*$H$6),Settings!$D$31)-MAX(G58,Settings!$C$31))*Settings!$C$32+MAX(0,(G58+(C58/1000*Settings!$B$16*$H$6))-MAX(G58,Settings!$D$31))*Settings!$D$32) | G58: =IF(C58="","",SUM($J$9:J57)) | H58: =IF(OR(C58="",C58=0),"",(F58-(C58/1000*Settings!$B$16*$H$6))/(C58/1000*Settings!$B$16*$H$6)) | I58: =IF(C58="","",IF(AND(G58<Settings!$B$31,(G58+F58)>=Settings!$B$31),Settings!$B$33,0)+IF(AND(G58<Settings!$C$31,(G58+F58)>=Settings!$C$31),Settings!$C$33,0)+IF(AND(G58<Settings!$D$31,(G58+F58)>=Settings!$D$31),Settings!$D$33,0)) | J58: =IF(C58="","",F58+I58)
A60: YEAR TOTALS | C60: =SUM(C9:C58) -> 7000000 | D60: =SUM(D9:D58) -> 560000 | E60: =SUM(E9:E58) -> 6440000 | F60: =SUM(F9:F58) -> 7350 | I60: =SUM(I9:I58) -> 300 | J60: =SUM(J9:J58) -> 7650
A62: 📅 YEAR-END REVIEW — NEXT YEAR'S TIERS
A63: Annual sale value (₹): | B63: =C60 -> 7000000
A65: DISCOUNT TIER
A66: This year (locked): | B66: =E5 -> Gold
A67: Next year: | B67: =IF(B63>=Settings!D9,"Diamond",IF(B63>=Settings!C9,"Platinum",IF(B63>=Settings!B9,"Gold",IF(E5="Diamond","Platinum",IF(E5="Platinum","Gold","Gold"))))) -> Diamond
A68: Change: | B68: =IF(B67=E5,"→ HOLD",IF(OR(AND(E5="Gold",B67="Platinum"),AND(E5="Gold",B67="Diamond"),AND(E5="Platinum",B67="Diamond")),"↑ UPGRADE","↓ DOWNGRADE")) -> ↑ UPGRADE
A75: POINTS REDEMPTION VALUE
A76: Total points earned: | B76: =J60 -> 7650
A77: ₹ conversion rate (current points tier): | B77: =IF(H5="Diamond",Settings!D26,IF(H5="Platinum",Settings!C26,Settings!B26)) -> 1
A78: Cash value (₹): | B78: =B76*B77 -> 7650

Sheet projections
A1: 📊 TIER QUALIFICATION — ANNUAL SALE VALUE NEEDED
A2: Both Discount and Points tiers qualify on annual sale value only.
A4: Tier | B4: Annual sale value (Discount) | C4: Discount rate | D4: Annual sale value (Points) | E4: Points multiplier | F4: ₹ / point
A5: Gold 🥇 | B5: =Settings!B9 -> 1000000 | C5: =Settings!B10 -> 0.08 | D5: =Settings!B14 -> 3000000 | E5: =Settings!B15 -> 1 | F5: =Settings!B26 -> 1
A6: Platinum 💎 | B6: =Settings!C9 -> 3000000 | C6: =Settings!C10 -> 0.1 | D6: =Settings!C14 -> 7000000 | E6: =Settings!C15 -> 1.5 | F6: =Settings!C26 -> 1.25
A7: Diamond 👑 | B7: =Settings!D9 -> 5000000 | C7: =Settings!D10 -> 0.12 | D7: =Settings!D14 -> 7100000 | E7: =Settings!D15 -> 2 | F7: =Settings!D26 -> 1.7
A9: Note: Members are evaluated independently on each tier at year-end. A member can be Discount-Gold and Points-Platinum simultaneously.

Sheet Revenue Impact
A2: 📊 PROGRAM REVENUE IMPACT
A3: Cost of the program is the discount given to members + the cash value of points they redeem. Both depend on the member's tier (locked annually).
A5: A. CURRENT MEMBER (from Bill Calculator)
A6: Total invoice value (₹) | B6: ='Bill Calculator'!C60 -> 7000000
A7: Discount given (₹) | B7: ='Bill Calculator'!D60 -> 560000
A8: Net invoice value (₹) | B8: ='Bill Calculator'!E60 -> 6440000
A9: Points earned | B9: ='Bill Calculator'!J60 -> 7650
A10: Cash value of points (if redeemed) | B10: ='Bill Calculator'!B78 -> 7650
A11: Total program cost (discount + points value) | B11: =B7+B10 -> 567650 | D11: `
A12: Cost as % of invoice value | B12: =IFERROR(B11/B6,0) -> 0.081092857
A14: B. PER-TIER COST TABLE (cost % of invoice if member earns and redeems all points)
B16: Discount-Gold | C16: Discount-Platinum | D16: Discount-Diamond
A17: Discount rate | B17: =Settings!B10 -> 0.08 | C17: =Settings!C10 -> 0.1 | D17: =Settings!D10 -> 0.12
A19: Points cost (assume all redeemed at points-tier rate ⃖) | B19: Pts-Gold | C19: Pts-Platinum | D19: Pts-Diamond
A20: Effective ₹ cost per ₹1,000 invoice | B20: =Settings!B17*Settings!B26 -> 1 | C20: =Settings!C17*Settings!C26 -> 1.875 | D20: =Settings!D17*Settings!D26 -> 3.4
A21: Points cost as % of invoice | B21: =B20/1000 -> 0.001 | C21: =C20/1000 -> 0.001875 | D21: =D20/1000 -> 0.0034
A23: C. WORST-CASE COMBINED COST (highest discount tier + highest points tier)
A24: Member is Discount-Diamond AND Points-Diamond | B24: =Settings!D10+D21 -> 0.1234
A25: Member is Discount-Platinum AND Points-Platinum | B25: =Settings!C10+C21 -> 0.101875
A26: Member is Discount-Gold AND Points-Gold | B26: =Settings!B10+B21 -> 0.081
A28: D. MARGIN CHECK
A29: Your gross margin on tile sales (%) | B29: 0.22
A30: Net margin after worst-case program cost (Diamond+Diamond) | B30: =B29-B24 -> 0.0966
A31: Net margin after baseline program cost (Gold+Gold) | B31: =B29-B26 -> 0.139
A33: Note: Per-purchase discount overrides set in software will affect realized cost.

Sheet Portfolio Tracker
A2: 👥 PORTFOLIO TRACKER — ALL MEMBERS
A3: One row per engineer/contractor. Both tiers are locked for the year. Discount and points-cost rates pull from Settings.
A5: # | B5: Member name | C5: Discount tier (this year) | D5: Points tier (this year) | E5: Annual invoice value (₹) | F5: Discount rate | G5: Discount given (₹) | H5: Points earned | I5: Points cash value (₹) | J5: Total program cost (₹) | K5: Cost % of invoice
A6: 1 | F6: =IF(C6="","",IF(C6="Diamond",Settings!$D$10,IF(C6="Platinum",Settings!$C$10,IF(C6="Gold",Settings!$B$10,"")))) | G6: =IF(OR(E6="",F6=""),"",E6*F6) | H6: =IF(OR(D6="",E6=""),"",E6/1000*Settings!$B$16*IF(D6="Diamond",Settings!$D$15,IF(D6="Platinum",Settings!$C$15,Settings!$B$15))) | I6: =IF(OR(D6="",H6=""),"",H6*IF(D6="Diamond",Settings!$D$26,IF(D6="Platinum",Settings!$C$26,Settings!$B$26))) | J6: =IFERROR(IF(G6="",0,G6)+IF(I6="",0,I6),0) -> 0 | K6: =IFERROR(J6/E6,0) -> 0
A7: 2 | F7: =IF(C7="","",IF(C7="Diamond",Settings!$D$10,IF(C7="Platinum",Settings!$C$10,IF(C7="Gold",Settings!$B$10,"")))) | G7: =IF(OR(E7="",F7=""),"",E7*F7) | H7: =IF(OR(D7="",E7=""),"",E7/1000*Settings!$B$16*IF(D7="Diamond",Settings!$D$15,IF(D7="Platinum",Settings!$C$15,Settings!$B$15))) | I7: =IF(OR(D7="",H7=""),"",H7*IF(D7="Diamond",Settings!$D$26,IF(D7="Platinum",Settings!$C$26,Settings!$B$26))) | J7: =IFERROR(IF(G7="",0,G7)+IF(I7="",0,I7),0) -> 0 | K7: =IFERROR(J7/E7,0) -> 0
A8: 3 | F8: =IF(C8="","",IF(C8="Diamond",Settings!$D$10,IF(C8="Platinum",Settings!$C$10,IF(C8="Gold",Settings!$B$10,"")))) | G8: =IF(OR(E8="",F8=""),"",E8*F8) | H8: =IF(OR(D8="",E8=""),"",E8/1000*Settings!$B$16*IF(D8="Diamond",Settings!$D$15,IF(D8="Platinum",Settings!$C$15,Settings!$B$15))) | I8: =IF(OR(D8="",H8=""),"",H8*IF(D8="Diamond",Settings!$D$26,IF(D8="Platinum",Settings!$C$26,Settings!$B$26))) | J8: =IFERROR(IF(G8="",0,G8)+IF(I8="",0,I8),0) -> 0 | K8: =IFERROR(J8/E8,0) -> 0
A9: 4 | F9: =IF(C9="","",IF(C9="Diamond",Settings!$D$10,IF(C9="Platinum",Settings!$C$10,IF(C9="Gold",Settings!$B$10,"")))) | G9: =IF(OR(E9="",F9=""),"",E9*F9) | H9: =IF(OR(D9="",E9=""),"",E9/1000*Settings!$B$16*IF(D9="Diamond",Settings!$D$15,IF(D9="Platinum",Settings!$C$15,Settings!$B$15))) | I9: =IF(OR(D9="",H9=""),"",H9*IF(D9="Diamond",Settings!$D$26,IF(D9="Platinum",Settings!$C$26,Settings!$B$26))) | J9: =IFERROR(IF(G9="",0,G9)+IF(I9="",0,I9),0) -> 0 | K9: =IFERROR(J9/E9,0) -> 0
A10: 5 | F10: =IF(C10="","",IF(C10="Diamond",Settings!$D$10,IF(C10="Platinum",Settings!$C$10,IF(C10="Gold",Settings!$B$10,"")))) | G10: =IF(OR(E10="",F10=""),"",E10*F10) | H10: =IF(OR(D10="",E10=""),"",E10/1000*Settings!$B$16*IF(D10="Diamond",Settings!$D$15,IF(D10="Platinum",Settings!$C$15,Settings!$B$15))) | I10: =IF(OR(D10="",H10=""),"",H10*IF(D10="Diamond",Settings!$D$26,IF(D10="Platinum",Settings!$C$26,Settings!$B$26))) | J10: =IFERROR(IF(G10="",0,G10)+IF(I10="",0,I10),0) -> 0 | K10: =IFERROR(J10/E10,0) -> 0
A11: 6 | F11: =IF(C11="","",IF(C11="Diamond",Settings!$D$10,IF(C11="Platinum",Settings!$C$10,IF(C11="Gold",Settings!$B$10,"")))) | G11: =IF(OR(E11="",F11=""),"",E11*F11) | H11: =IF(OR(D11="",E11=""),"",E11/1000*Settings!$B$16*IF(D11="Diamond",Settings!$D$15,IF(D11="Platinum",Settings!$C$15,Settings!$B$15))) | I11: =IF(OR(D11="",H11=""),"",H11*IF(D11="Diamond",Settings!$D$26,IF(D11="Platinum",Settings!$C$26,Settings!$B$26))) | J11: =IFERROR(IF(G11="",0,G11)+IF(I11="",0,I11),0) -> 0 | K11: =IFERROR(J11/E11,0) -> 0
A12: 7 | F12: =IF(C12="","",IF(C12="Diamond",Settings!$D$10,IF(C12="Platinum",Settings!$C$10,IF(C12="Gold",Settings!$B$10,"")))) | G12: =IF(OR(E12="",F12=""),"",E12*F12) | H12: =IF(OR(D12="",E12=""),"",E12/1000*Settings!$B$16*IF(D12="Diamond",Settings!$D$15,IF(D12="Platinum",Settings!$C$15,Settings!$B$15))) | I12: =IF(OR(D12="",H12=""),"",H12*IF(D12="Diamond",Settings!$D$26,IF(D12="Platinum",Settings!$C$26,Settings!$B$26))) | J12: =IFERROR(IF(G12="",0,G12)+IF(I12="",0,I12),0) -> 0 | K12: =IFERROR(J12/E12,0) -> 0
A13: 8 | F13: =IF(C13="","",IF(C13="Diamond",Settings!$D$10,IF(C13="Platinum",Settings!$C$10,IF(C13="Gold",Settings!$B$10,"")))) | G13: =IF(OR(E13="",F13=""),"",E13*F13) | H13: =IF(OR(D13="",E13=""),"",E13/1000*Settings!$B$16*IF(D13="Diamond",Settings!$D$15,IF(D13="Platinum",Settings!$C$15,Settings!$B$15))) | I13: =IF(OR(D13="",H13=""),"",H13*IF(D13="Diamond",Settings!$D$26,IF(D13="Platinum",Settings!$C$26,Settings!$B$26))) | J13: =IFERROR(IF(G13="",0,G13)+IF(I13="",0,I13),0) -> 0 | K13: =IFERROR(J13/E13,0) -> 0
A14: 9 | F14: =IF(C14="","",IF(C14="Diamond",Settings!$D$10,IF(C14="Platinum",Settings!$C$10,IF(C14="Gold",Settings!$B$10,"")))) | G14: =IF(OR(E14="",F14=""),"",E14*F14) | H14: =IF(OR(D14="",E14=""),"",E14/1000*Settings!$B$16*IF(D14="Diamond",Settings!$D$15,IF(D14="Platinum",Settings!$C$15,Settings!$B$15))) | I14: =IF(OR(D14="",H14=""),"",H14*IF(D14="Diamond",Settings!$D$26,IF(D14="Platinum",Settings!$C$26,Settings!$B$26))) | J14: =IFERROR(IF(G14="",0,G14)+IF(I14="",0,I14),0) -> 0 | K14: =IFERROR(J14/E14,0) -> 0
A15: 10 | F15: =IF(C15="","",IF(C15="Diamond",Settings!$D$10,IF(C15="Platinum",Settings!$C$10,IF(C15="Gold",Settings!$B$10,"")))) | G15: =IF(OR(E15="",F15=""),"",E15*F15) | H15: =IF(OR(D15="",E15=""),"",E15/1000*Settings!$B$16*IF(D15="Diamond",Settings!$D$15,IF(D15="Platinum",Settings!$C$15,Settings!$B$15))) | I15: =IF(OR(D15="",H15=""),"",H15*IF(D15="Diamond",Settings!$D$26,IF(D15="Platinum",Settings!$C$26,Settings!$B$26))) | J15: =IFERROR(IF(G15="",0,G15)+IF(I15="",0,I15),0) -> 0 | K15: =IFERROR(J15/E15,0) -> 0
A16: 11 | F16: =IF(C16="","",IF(C16="Diamond",Settings!$D$10,IF(C16="Platinum",Settings!$C$10,IF(C16="Gold",Settings!$B$10,"")))) | G16: =IF(OR(E16="",F16=""),"",E16*F16) | H16: =IF(OR(D16="",E16=""),"",E16/1000*Settings!$B$16*IF(D16="Diamond",Settings!$D$15,IF(D16="Platinum",Settings!$C$15,Settings!$B$15))) | I16: =IF(OR(D16="",H16=""),"",H16*IF(D16="Diamond",Settings!$D$26,IF(D16="Platinum",Settings!$C$26,Settings!$B$26))) | J16: =IFERROR(IF(G16="",0,G16)+IF(I16="",0,I16),0) -> 0 | K16: =IFERROR(J16/E16,0) -> 0
A17: 12 | F17: =IF(C17="","",IF(C17="Diamond",Settings!$D$10,IF(C17="Platinum",Settings!$C$10,IF(C17="Gold",Settings!$B$10,"")))) | G17: =IF(OR(E17="",F17=""),"",E17*F17) | H17: =IF(OR(D17="",E17=""),"",E17/1000*Settings!$B$16*IF(D17="Diamond",Settings!$D$15,IF(D17="Platinum",Settings!$C$15,Settings!$B$15))) | I17: =IF(OR(D17="",H17=""),"",H17*IF(D17="Diamond",Settings!$D$26,IF(D17="Platinum",Settings!$C$26,Settings!$B$26))) | J17: =IFERROR(IF(G17="",0,G17)+IF(I17="",0,I17),0) -> 0 | K17: =IFERROR(J17/E17,0) -> 0
... A35: 30 | F35: =IF(C35="","",IF(C35="Diamond",Settings!$D$10,IF(C35="Platinum",Settings!$C$10,IF(C35="Gold",Settings!$B$10,"")))) | G35: =IF(OR(E35="",F35=""),"",E35*F35) | H35: =IF(OR(D35="",E35=""),"",E35/1000*Settings!$B$16*IF(D35="Diamond",Settings!$D$15,IF(D35="Platinum",Settings!$C$15,Settings!$B$15))) | I35: =IF(OR(D35="",H35=""),"",H35*IF(D35="Diamond",Settings!$D$26,IF(D35="Platinum",Settings!$C$26,Settings!$B$26))) | J35: =IFERROR(IF(G35="",0,G35)+IF(I35="",0,I35),0) -> 0 | K35: =IFERROR(J35/E35,0) -> 0
A37: PORTFOLIO TOTALS | E37: =SUM(E6:E35) -> 0 | G37: =SUM(G6:G35) -> 0 | H37: =SUM(H6:H35) -> 0 | I37: =SUM(I6:I35) -> 0 | J37: =SUM(J6:J35) -> 0 | K37: =IFERROR(J37/E37,0) -> 0

Sheet Members
A1: 👥 MEMBERS
A2: One row per programme participant. Member ID links to the Invoice Log. Discount tier dropdown shows tier + locked rate for the year.
A3: 🔵 Blue cells = manual input ⚫ Black = derived
A5: ID | B5: Name | C5: Phone | D5: Type | E5: Branch | F5: Joined | G5: Discount tier (locked for year) | H5: Custom % | I5: Status | J5: YTD Sale (₹) | K5: YTD Discount (₹) | L5: Effective %
A6: M001 | B6: Rajesh Kumar | C6: 9876543210 | D6: Engineer | E6: Madurai | F6: 45292 | G6: 🥇 Gold (8%) | H6: 0.2 | I6: Active | J6: =IF($A6="","",SUMIFS('Invoice Log'!$F:$F,'Invoice Log'!$C:$C,$A6,'Invoice Log'!$K:$K,"Confirmed")) -> 2000000 | K6: =IF($A6="","",SUMIFS('Invoice Log'!$H:$H,'Invoice Log'!$C:$C,$A6,'Invoice Log'!$K:$K,"Confirmed")) -> 400000 | L6: =IF(OR($A6="",J6="",J6=0),"",K6/J6) -> 0.2
A7: M002 | B7: test | C7: 9876543213 | D7: Engineer | E7: Ramnad | F7: 46148 | G7: 💎 Platinum (10%) | I7: Active | J7: =IF($A7="","",SUMIFS('Invoice Log'!$F:$F,'Invoice Log'!$C:$C,$A7,'Invoice Log'!$K:$K,"Confirmed")) -> 3000000 | K7: =IF($A7="","",SUMIFS('Invoice Log'!$H:$H,'Invoice Log'!$C:$C,$A7,'Invoice Log'!$K:$K,"Confirmed")) -> 300000 | L7: =IF(OR($A7="",J7="",J7=0),"",K7/J7) -> 0.1
J8: =IF($A8="","",SUMIFS('Invoice Log'!$F:$F,'Invoice Log'!$C:$C,$A8,'Invoice Log'!$K:$K,"Confirmed")) | K8: =IF($A8="","",SUMIFS('Invoice Log'!$H:$H,'Invoice Log'!$C:$C,$A8,'Invoice Log'!$K:$K,"Confirmed")) | L8: =IF(OR($A8="",J8="",J8=0),"",K8/J8)
J9: =IF($A9="","",SUMIFS('Invoice Log'!$F:$F,'Invoice Log'!$C:$C,$A9,'Invoice Log'!$K:$K,"Confirmed")) | K9: =IF($A9="","",SUMIFS('Invoice Log'!$H:$H,'Invoice Log'!$C:$C,$A9,'Invoice Log'!$K:$K,"Confirmed")) | L9: =IF(OR($A9="",J9="",J9=0),"",K9/J9)
J10: =IF($A10="","",SUMIFS('Invoice Log'!$F:$F,'Invoice Log'!$C:$C,$A10,'Invoice Log'!$K:$K,"Confirmed")) | K10: =IF($A10="","",SUMIFS('Invoice Log'!$H:$H,'Invoice Log'!$C:$C,$A10,'Invoice Log'!$K:$K,"Confirmed")) | L10: =IF(OR($A10="",J10="",J10=0),"",K10/J10)
J11: =IF($A11="","",SUMIFS('Invoice Log'!$F:$F,'Invoice Log'!$C:$C,$A11,'Invoice Log'!$K:$K,"Confirmed")) | K11: =IF($A11="","",SUMIFS('Invoice Log'!$H:$H,'Invoice Log'!$C:$C,$A11,'Invoice Log'!$K:$K,"Confirmed")) | L11: =IF(OR($A11="",J11="",J11=0),"",K11/J11)
J12: =IF($A12="","",SUMIFS('Invoice Log'!$F:$F,'Invoice Log'!$C:$C,$A12,'Invoice Log'!$K:$K,"Confirmed")) | K12: =IF($A12="","",SUMIFS('Invoice Log'!$H:$H,'Invoice Log'!$C:$C,$A12,'Invoice Log'!$K:$K,"Confirmed")) | L12: =IF(OR($A12="",J12="",J12=0),"",K12/J12)
J13: =IF($A13="","",SUMIFS('Invoice Log'!$F:$F,'Invoice Log'!$C:$C,$A13,'Invoice Log'!$K:$K,"Confirmed")) | K13: =IF($A13="","",SUMIFS('Invoice Log'!$H:$H,'Invoice Log'!$C:$C,$A13,'Invoice Log'!$K:$K,"Confirmed")) | L13: =IF(OR($A13="",J13="",J13=0),"",K13/J13)
J14: =IF($A14="","",SUMIFS('Invoice Log'!$F:$F,'Invoice Log'!$C:$C,$A14,'Invoice Log'!$K:$K,"Confirmed")) | K14: =IF($A14="","",SUMIFS('Invoice Log'!$H:$H,'Invoice Log'!$C:$C,$A14,'Invoice Log'!$K:$K,"Confirmed")) | L14: =IF(OR($A14="",J14="",J14=0),"",K14/J14)
J15: =IF($A15="","",SUMIFS('Invoice Log'!$F:$F,'Invoice Log'!$C:$C,$A15,'Invoice Log'!$K:$K,"Confirmed")) | K15: =IF($A15="","",SUMIFS('Invoice Log'!$H:$H,'Invoice Log'!$C:$C,$A15,'Invoice Log'!$K:$K,"Confirmed")) | L15: =IF(OR($A15="",J15="",J15=0),"",K15/J15)
J16: =IF($A16="","",SUMIFS('Invoice Log'!$F:$F,'Invoice Log'!$C:$C,$A16,'Invoice Log'!$K:$K,"Confirmed")) | K16: =IF($A16="","",SUMIFS('Invoice Log'!$H:$H,'Invoice Log'!$C:$C,$A16,'Invoice Log'!$K:$K,"Confirmed")) | L16: =IF(OR($A16="",J16="",J16=0),"",K16/J16)
J17: =IF($A17="","",SUMIFS('Invoice Log'!$F:$F,'Invoice Log'!$C:$C,$A17,'Invoice Log'!$K:$K,"Confirmed")) | K17: =IF($A17="","",SUMIFS('Invoice Log'!$H:$H,'Invoice Log'!$C:$C,$A17,'Invoice Log'!$K:$K,"Confirmed")) | L17: =IF(OR($A17="",J17="",J17=0),"",K17/J17)
J18: =IF($A18="","",SUMIFS('Invoice Log'!$F:$F,'Invoice Log'!$C:$C,$A18,'Invoice Log'!$K:$K,"Confirmed")) | K18: =IF($A18="","",SUMIFS('Invoice Log'!$H:$H,'Invoice Log'!$C:$C,$A18,'Invoice Log'!$K:$K,"Confirmed")) | L18: =IF(OR($A18="",J18="",J18=0),"",K18/J18)
J19: =IF($A19="","",SUMIFS('Invoice Log'!$F:$F,'Invoice Log'!$C:$C,$A19,'Invoice Log'!$K:$K,"Confirmed")) | K19: =IF($A19="","",SUMIFS('Invoice Log'!$H:$H,'Invoice Log'!$C:$C,$A19,'Invoice Log'!$K:$K,"Confirmed"))
J20: =IF($B20="","",IFERROR(_xlfn.XLOOKUP($B20,Members!$C:$C,Members!$G:$G),"")) | K20: =IF($A20="","",SUMIFS('Invoice Log'!$H:$H,'Invoice Log'!$C:$C,$A20,'Invoice Log'!$K:$K,"Confirmed"))
J21: =IF($B21="","",IFERROR(_xlfn.XLOOKUP($B21,Members!$C:$C,Members!$G:$G),"")) | K21: =IF($A21="","",SUMIFS('Invoice Log'!$H:$H,'Invoice Log'!$C:$C,$A21,'Invoice Log'!$K:$K,"Confirmed"))
J22: =IF($B22="","",IFERROR(_xlfn.XLOOKUP($B22,Members!$C:$C,Members!$G:$G),"")) | K22: =IF($A22="","",SUMIFS('Invoice Log'!$H:$H,'Invoice Log'!$C:$C,$A22,'Invoice Log'!$K:$K,"Confirmed"))
J23: =IF($B23="","",IFERROR(_xlfn.XLOOKUP($B23,Members!$C:$C,Members!$G:$G),"")) | K23: =IF($A23="","",SUMIFS('Invoice Log'!$H:$H,'Invoice Log'!$C:$C,$A23,'Invoice Log'!$K:$K,"Confirmed"))
J24: =IF($B24="","",IFERROR(_xlfn.XLOOKUP($B24,Members!$C:$C,Members!$G:$G),"")) | K24: =IF($A24="","",SUMIFS('Invoice Log'!$H:$H,'Invoice Log'!$C:$C,$A24,'Invoice Log'!$K:$K,"Confirmed"))
J25: =IF($B25="","",IFERROR(_xlfn.XLOOKUP($B25,Members!$C:$C,Members!$G:$G),"")) | K25: =IF($A25="","",SUMIFS('Invoice Log'!$H:$H,'Invoice Log'!$C:$C,$A25,'Invoice Log'!$K:$K,"Confirmed"))
J26: =IF($B26="","",IFERROR(_xlfn.XLOOKUP($B26,Members!$C:$C,Members!$G:$G),"")) | K26: Confirmed
J27: =IF($B27="","",IFERROR(_xlfn.XLOOKUP($B27,Members!$C:$C,Members!$G:$G),"")) | K27: Confirmed
J28: =IF($B28="","",IFERROR(_xlfn.XLOOKUP($B28,Members!$C:$C,Members!$G:$G),"")) | K28: Confirmed
J29: =IF($B29="","",IFERROR(_xlfn.XLOOKUP($B29,Members!$C:$C,Members!$G:$G),"")) | K29: Confirmed
J30: =IF($B30="","",IFERROR(_xlfn.XLOOKUP($B30,Members!$C:$C,Members!$G:$G),"")) | K30: Confirmed
J31: =IF($B31="","",IFERROR(_xlfn.XLOOKUP($B31,Members!$C:$C,Members!$G:$G),"")) | K31: Confirmed
J32: =IF($B32="","",IFERROR(_xlfn.XLOOKUP($B32,Members!$C:$C,Members!$G:$G),"")) | K32: Confirmed
J33: =IF($B33="","",IFERROR(_xlfn.XLOOKUP($B33,Members!$C:$C,Members!$G:$G),"")) | K33: Confirmed
J34: =IF($B34="","",IFERROR(_xlfn.XLOOKUP($B34,Members!$C:$C,Members!$G:$G),"")) | K34: Confirmed
J35: =IF($B35="","",IFERROR(_xlfn.XLOOKUP($B35,Members!$C:$C,Members!$G:$G),"")) | K35: Confirmed
J36: =IF($B36="","",IFERROR(_xlfn.XLOOKUP($B36,Members!$C:$C,Members!$G:$G),"")) | K36: Confirmed
J37: =IF($B37="","",IFERROR(_xlfn.XLOOKUP($B37,Members!$C:$C,Members!$G:$G),"")) | K37: Confirmed
... J55: =IF($B55="","",IFERROR(_xlfn.XLOOKUP($B55,Members!$C:$C,Members!$G:$G),"")) | K55: Confirmed
A56: TOTAL | B56: ="Members: "&COUNTA(A6:A55) -> Members: 2 | J56: =SUM(J6:J55) -> 5000000 | K56: =SUM(K6:K55) -> 700000 | L56: =IFERROR(K56/J56,0) -> 0.14

Sheet Invoice Log
A1: 📄 INVOICE LOG — Every invoice across all members
A2: One row per invoice. Member ID (col B) links to the Members sheet. Discount, points, and bonuses are calculated using the member's locked tier from Members sheet.
A3: Blue cells = manual input. Black = derived. The Members sheet aggregates YTD totals via SUMIFS on column B.
A5: Invoice # | B5: Phone (input) | C5: Member ID | D5: Member name | E5: Invoice date | F5: Invoice value (₹) | G5: Project / description | H5: Discount (₹) | I5: Net invoice (₹) | J5: Discount tier | K5: Status | L5: Notes
A6: INV-0001 | B6: 9876543210 | C6: =IF($B6="","",IFERROR(_xlfn.XLOOKUP($B6,Members!$C:$C,Members!$A:$A),"NOT FOUND")) -> M001 | D6: =IF($B6="","",IFERROR(_xlfn.XLOOKUP($B6,Members!$C:$C,Members!$B:$B),"NOT FOUND")) -> Rajesh Kumar | E6: 45292 | F6: 2000000 | G6: Sample project — replace | H6: =IF(OR($B6="",$F6=""),"",$F6*IFERROR(IF(AND(_xlfn.XLOOKUP($B6,Members!$C:$C,Members!$H:$H)<>"",ISNUMBER(_xlfn.XLOOKUP($B6,Members!$C:$C,Members!$H:$H))),_xlfn.XLOOKUP($B6,Members!$C:$C,Members!$H:$H),IF(ISNUMBER(SEARCH("Diamond",J6)),Settings!$D$10,IF(ISNUMBER(SEARCH("Platinum",J6)),Settings!$C$10,Settings!$B$10))),0)) -> 400000 | I6: =IF(OR($F6="",$H6=""),"",$F6-$H6) -> 1600000 | J6: =IF($B6="","",IFERROR(_xlfn.XLOOKUP($B6,Members!$C:$C,Members!$G:$G),"")) -> 🥇 Gold (8%) | K6: Confirmed
A7: INV-0001 | B7: 9876543213 | C7: =IF($B7="","",IFERROR(_xlfn.XLOOKUP($B7,Members!$C:$C,Members!$A:$A),"NOT FOUND")) -> M002 | D7: =IF($B7="","",IFERROR(_xlfn.XLOOKUP($B7,Members!$C:$C,Members!$B:$B),"NOT FOUND")) -> test | E7: 45292 | F7: 3000000 | G7: Sample project — replace | H7: =IF(OR($B7="",$F7=""),"",$F7*IFERROR(IF(AND(_xlfn.XLOOKUP($B7,Members!$C:$C,Members!$H:$H)<>"",ISNUMBER(_xlfn.XLOOKUP($B7,Members!$C:$C,Members!$H:$H))),_xlfn.XLOOKUP($B7,Members!$C:$C,Members!$H:$H),IF(ISNUMBER(SEARCH("Diamond",J7)),Settings!$D$10,IF(ISNUMBER(SEARCH("Platinum",J7)),Settings!$C$10,Settings!$B$10))),0)) -> 300000 | I7: =IF(OR($F7="",$H7=""),"",$F7-$H7) -> 2700000 | J7: =IF($B7="","",IFERROR(_xlfn.XLOOKUP($B7,Members!$C:$C,Members!$G:$G),"")) -> 💎 Platinum (10%) | K7: Confirmed
A8: INV-0001 | B8: 9876543210 | C8: =IF($B8="","",IFERROR(_xlfn.XLOOKUP($B8,Members!$C:$C,Members!$A:$A),"NOT FOUND")) -> NOT FOUND | D8: =IF($B8="","",IFERROR(_xlfn.XLOOKUP($B8,Members!$C:$C,Members!$B:$B),"NOT FOUND")) -> NOT FOUND | E8: 45292 | F8: 2000000 | G8: Sample project — replace | H8: =IF(OR($B8="",$F8=""),"",$F8*IFERROR(IF(AND(_xlfn.XLOOKUP($B8,Members!$C:$C,Members!$H:$H)<>"",ISNUMBER(_xlfn.XLOOKUP($B8,Members!$C:$C,Members!$H:$H))),_xlfn.XLOOKUP($B8,Members!$C:$C,Members!$H:$H),IF(ISNUMBER(SEARCH("Diamond",J8)),Settings!$D$10,IF(ISNUMBER(SEARCH("Platinum",J8)),Settings!$C$10,Settings!$B$10))),0)) -> 0 | I8: =IF(OR($F8="",$H8=""),"",$F8-$H8) -> 2000000 | J8: =IF($B8="","",IFERROR(_xlfn.XLOOKUP($B8,Members!$C:$C,Members!$G:$G),"")) | K8: Confirmed
A9: INV-0001 | B9: 9876543210 | C9: =IF($B9="","",IFERROR(_xlfn.XLOOKUP($B9,Members!$C:$C,Members!$A:$A),"NOT FOUND")) -> NOT FOUND | D9: =IF($B9="","",IFERROR(_xlfn.XLOOKUP($B9,Members!$C:$C,Members!$B:$B),"NOT FOUND")) -> NOT FOUND | E9: 45292 | F9: 2000000 | G9: Sample project — replace | H9: =IF(OR($B9="",$F9=""),"",$F9*IFERROR(IF(AND(_xlfn.XLOOKUP($B9,Members!$C:$C,Members!$H:$H)<>"",ISNUMBER(_xlfn.XLOOKUP($B9,Members!$C:$C,Members!$H:$H))),_xlfn.XLOOKUP($B9,Members!$C:$C,Members!$H:$H),IF(ISNUMBER(SEARCH("Diamond",J9)),Settings!$D$10,IF(ISNUMBER(SEARCH("Platinum",J9)),Settings!$C$10,Settings!$B$10))),0)) -> 0 | I9: =IF(OR($F9="",$H9=""),"",$F9-$H9) -> 2000000 | J9: =IF($B9="","",IFERROR(_xlfn.XLOOKUP($B9,Members!$C:$C,Members!$G:$G),"")) | K9: Confirmed
A10: INV-0001 | B10: 9876543210 | C10: =IF($B10="","",IFERROR(_xlfn.XLOOKUP($B10,Members!$C:$C,Members!$A:$A),"NOT FOUND")) -> NOT FOUND | D10: =IF($B10="","",IFERROR(_xlfn.XLOOKUP($B10,Members!$C:$C,Members!$B:$B),"NOT FOUND")) -> NOT FOUND | E10: 45292 | F10: 2000000 | G10: Sample project — replace | H10: =IF(OR($B10="",$F10=""),"",$F10*IFERROR(IF(AND(_xlfn.XLOOKUP($B10,Members!$C:$C,Members!$H:$H)<>"",ISNUMBER(_xlfn.XLOOKUP($B10,Members!$C:$C,Members!$H:$H))),_xlfn.XLOOKUP($B10,Members!$C:$C,Members!$H:$H),IF(ISNUMBER(SEARCH("Diamond",J10)),Settings!$D$10,IF(ISNUMBER(SEARCH("Platinum",J10)),Settings!$C$10,Settings!$B$10))),0)) -> 0 | I10: =IF(OR($F10="",$H10=""),"",$F10-$H10) -> 2000000 | J10: . | K10: Confirmed
A11: INV-0001 | B11: 9876543210 | C11: =IF($B11="","",IFERROR(_xlfn.XLOOKUP($B11,Members!$C:$C,Members!$A:$A),"NOT FOUND")) -> NOT FOUND | D11: =IF($B11="","",IFERROR(_xlfn.XLOOKUP($B11,Members!$C:$C,Members!$B:$B),"NOT FOUND")) -> NOT FOUND | E11: 45292 | F11: 2000000 | G11: Sample project — replace | H11: =IF(OR($B11="",$F11=""),"",$F11*IFERROR(IF(AND(_xlfn.XLOOKUP($B11,Members!$C:$C,Members!$H:$H)<>"",ISNUMBER(_xlfn.XLOOKUP($B11,Members!$C:$C,Members!$H:$H))),_xlfn.XLOOKUP($B11,Members!$C:$C,Members!$H:$H),IF(ISNUMBER(SEARCH("Diamond",J11)),Settings!$D$10,IF(ISNUMBER(SEARCH("Platinum",J11)),Settings!$C$10,Settings!$B$10))),0)) -> 0 | I11: =IF(OR($F11="",$H11=""),"",$F11-$H11) -> 2000000 | J11: =IF($B11="","",IFERROR(_xlfn.XLOOKUP($B11,Members!$C:$C,Members!$G:$G),"")) | K11: Confirmed
A12: INV-0001 | B12: 9876543210 | C12: =IF($B12="","",IFERROR(_xlfn.XLOOKUP($B12,Members!$C:$C,Members!$A:$A),"NOT FOUND")) -> NOT FOUND | D12: =IF($B12="","",IFERROR(_xlfn.XLOOKUP($B12,Members!$C:$C,Members!$B:$B),"NOT FOUND")) -> NOT FOUND | E12: 45292 | F12: 2000000 | G12: Sample project — replace | H12: =IF(OR($B12="",$F12=""),"",$F12*IFERROR(IF(AND(_xlfn.XLOOKUP($B12,Members!$C:$C,Members!$H:$H)<>"",ISNUMBER(_xlfn.XLOOKUP($B12,Members!$C:$C,Members!$H:$H))),_xlfn.XLOOKUP($B12,Members!$C:$C,Members!$H:$H),IF(ISNUMBER(SEARCH("Diamond",J12)),Settings!$D$10,IF(ISNUMBER(SEARCH("Platinum",J12)),Settings!$C$10,Settings!$B$10))),0)) -> 0 | I12: =IF(OR($F12="",$H12=""),"",$F12-$H12) -> 2000000 | J12: =IF($B12="","",IFERROR(_xlfn.XLOOKUP($B12,Members!$C:$C,Members!$G:$G),"")) | K12: Confirmed
A13: INV-0001 | B13: 9876543210 | C13: =IF($B13="","",IFERROR(_xlfn.XLOOKUP($B13,Members!$C:$C,Members!$A:$A),"NOT FOUND")) -> NOT FOUND | D13: =IF($B13="","",IFERROR(_xlfn.XLOOKUP($B13,Members!$C:$C,Members!$B:$B),"NOT FOUND")) -> NOT FOUND | E13: 45292 | F13: 2000000 | G13: Sample project — replace | H13: =IF(OR($B13="",$F13=""),"",$F13*IFERROR(IF(AND(_xlfn.XLOOKUP($B13,Members!$C:$C,Members!$H:$H)<>"",ISNUMBER(_xlfn.XLOOKUP($B13,Members!$C:$C,Members!$H:$H))),_xlfn.XLOOKUP($B13,Members!$C:$C,Members!$H:$H),IF(ISNUMBER(SEARCH("Diamond",J13)),Settings!$D$10,IF(ISNUMBER(SEARCH("Platinum",J13)),Settings!$C$10,Settings!$B$10))),0)) -> 0 | I13: =IF(OR($F13="",$H13=""),"",$F13-$H13) -> 2000000 | J13: =IF($B13="","",IFERROR(_xlfn.XLOOKUP($B13,Members!$C:$C,Members!$G:$G),"")) | K13: Confirmed
A14: INV-0001 | B14: 9876543210 | C14: =IF($B14="","",IFERROR(_xlfn.XLOOKUP($B14,Members!$C:$C,Members!$A:$A),"NOT FOUND")) -> NOT FOUND | D14: =IF($B14="","",IFERROR(_xlfn.XLOOKUP($B14,Members!$C:$C,Members!$B:$B),"NOT FOUND")) -> NOT FOUND | E14: 45292 | F14: 2000000 | G14: Sample project — replace | H14: =IF(OR($B14="",$F14=""),"",$F14*IFERROR(IF(AND(_xlfn.XLOOKUP($B14,Members!$C:$C,Members!$H:$H)<>"",ISNUMBER(_xlfn.XLOOKUP($B14,Members!$C:$C,Members!$H:$H))),_xlfn.XLOOKUP($B14,Members!$C:$C,Members!$H:$H),IF(ISNUMBER(SEARCH("Diamond",J14)),Settings!$D$10,IF(ISNUMBER(SEARCH("Platinum",J14)),Settings!$C$10,Settings!$B$10))),0)) -> 0 | I14: =IF(OR($F14="",$H14=""),"",$F14-$H14) -> 2000000 | J14: =IF($B14="","",IFERROR(_xlfn.XLOOKUP($B14,Members!$C:$C,Members!$G:$G),"")) | K14: Confirmed
A15: INV-0001 | B15: 9876543210 | C15: =IF($B15="","",IFERROR(_xlfn.XLOOKUP($B15,Members!$C:$C,Members!$A:$A),"NOT FOUND")) -> NOT FOUND | D15: =IF($B15="","",IFERROR(_xlfn.XLOOKUP($B15,Members!$C:$C,Members!$B:$B),"NOT FOUND")) -> NOT FOUND | E15: 45292 | F15: 2000000 | G15: Sample project — replace | H15: =IF(OR($B15="",$F15=""),"",$F15*IFERROR(IF(AND(_xlfn.XLOOKUP($B15,Members!$C:$C,Members!$H:$H)<>"",ISNUMBER(_xlfn.XLOOKUP($B15,Members!$C:$C,Members!$H:$H))),_xlfn.XLOOKUP($B15,Members!$C:$C,Members!$H:$H),IF(ISNUMBER(SEARCH("Diamond",J15)),Settings!$D$10,IF(ISNUMBER(SEARCH("Platinum",J15)),Settings!$C$10,Settings!$B$10))),0)) -> 0 | I15: =IF(OR($F15="",$H15=""),"",$F15-$H15) -> 2000000 | J15: =IF($B15="","",IFERROR(_xlfn.XLOOKUP($B15,Members!$C:$C,Members!$G:$G),"")) | K15: Confirmed
A16: INV-0001 | B16: 9876543210 | C16: =IF($B16="","",IFERROR(_xlfn.XLOOKUP($B16,Members!$C:$C,Members!$A:$A),"NOT FOUND")) -> NOT FOUND | D16: =IF($B16="","",IFERROR(_xlfn.XLOOKUP($B16,Members!$C:$C,Members!$B:$B),"NOT FOUND")) -> NOT FOUND | E16: 45292 | F16: 2000000 | G16: Sample project — replace | H16: =IF(OR($B16="",$F16=""),"",$F16*IFERROR(IF(AND(_xlfn.XLOOKUP($B16,Members!$C:$C,Members!$H:$H)<>"",ISNUMBER(_xlfn.XLOOKUP($B16,Members!$C:$C,Members!$H:$H))),_xlfn.XLOOKUP($B16,Members!$C:$C,Members!$H:$H),IF(ISNUMBER(SEARCH("Diamond",J16)),Settings!$D$10,IF(ISNUMBER(SEARCH("Platinum",J16)),Settings!$C$10,Settings!$B$10))),0)) -> 0 | I16: =IF(OR($F16="",$H16=""),"",$F16-$H16) -> 2000000 | J16: =IF($B16="","",IFERROR(_xlfn.XLOOKUP($B16,Members!$C:$C,Members!$G:$G),"")) | K16: Confirmed
A17: INV-0001 | B17: 9876543210 | C17: =IF($B17="","",IFERROR(_xlfn.XLOOKUP($B17,Members!$C:$C,Members!$A:$A),"NOT FOUND")) -> NOT FOUND | D17: =IF($B17="","",IFERROR(_xlfn.XLOOKUP($B17,Members!$C:$C,Members!$B:$B),"NOT FOUND")) -> NOT FOUND | E17: 45292 | F17: 2000000 | G17: Sample project — replace | H17: =IF(OR($B17="",$F17=""),"",$F17*IFERROR(IF(AND(_xlfn.XLOOKUP($B17,Members!$C:$C,Members!$H:$H)<>"",ISNUMBER(_xlfn.XLOOKUP($B17,Members!$C:$C,Members!$H:$H))),_xlfn.XLOOKUP($B17,Members!$C:$C,Members!$H:$H),IF(ISNUMBER(SEARCH("Diamond",J17)),Settings!$D$10,IF(ISNUMBER(SEARCH("Platinum",J17)),Settings!$C$10,Settings!$B$10))),0)) -> 0 | I17: =IF(OR($F17="",$H17=""),"",$F17-$H17) -> 2000000 | J17: =IF($B17="","",IFERROR(_xlfn.XLOOKUP($B17,Members!$C:$C,Members!$G:$G),"")) | K17: Confirmed
A18: INV-0001 | B18: 9876543210 | C18: =IF($B18="","",IFERROR(_xlfn.XLOOKUP($B18,Members!$C:$C,Members!$A:$A),"NOT FOUND")) -> NOT FOUND | D18: =IF($B18="","",IFERROR(_xlfn.XLOOKUP($B18,Members!$C:$C,Members!$B:$B),"NOT FOUND")) -> NOT FOUND | E18: 45292 | F18: 2000000 | G18: Sample project — replace | H18: =IF(OR($B18="",$F18=""),"",$F18*IFERROR(IF(AND(_xlfn.XLOOKUP($B18,Members!$C:$C,Members!$H:$H)<>"",ISNUMBER(_xlfn.XLOOKUP($B18,Members!$C:$C,Members!$H:$H))),_xlfn.XLOOKUP($B18,Members!$C:$C,Members!$H:$H),IF(ISNUMBER(SEARCH("Diamond",J18)),Settings!$D$10,IF(ISNUMBER(SEARCH("Platinum",J18)),Settings!$C$10,Settings!$B$10))),0)) -> 0 | I18: =IF(OR($F18="",$H18=""),"",$F18-$H18) -> 2000000 | J18: =IF($B18="","",IFERROR(_xlfn.XLOOKUP($B18,Members!$C:$C,Members!$G:$G),"")) | K18: Confirmed
A19: INV-0001 | B19: 9876543210 | C19: =IF($B19="","",IFERROR(_xlfn.XLOOKUP($B19,Members!$C:$C,Members!$A:$A),"NOT FOUND")) -> NOT FOUND | D19: =IF($B19="","",IFERROR(_xlfn.XLOOKUP($B19,Members!$C:$C,Members!$B:$B),"NOT FOUND")) -> NOT FOUND | E19: 45292 | F19: 2000000 | G19: Sample project — replace | H19: =IF(OR($B19="",$F19=""),"",$F19*IFERROR(IF(AND(_xlfn.XLOOKUP($B19,Members!$C:$C,Members!$H:$H)<>"",ISNUMBER(_xlfn.XLOOKUP($B19,Members!$C:$C,Members!$H:$H))),_xlfn.XLOOKUP($B19,Members!$C:$C,Members!$H:$H),IF(ISNUMBER(SEARCH("Diamond",J19)),Settings!$D$10,IF(ISNUMBER(SEARCH("Platinum",J19)),Settings!$C$10,Settings!$B$10))),0)) -> 0 | I19: =IF(OR($F19="",$H19=""),"",$F19-$H19) -> 2000000 | J19: =IF($B19="","",IFERROR(_xlfn.XLOOKUP($B19,Members!$C:$C,Members!$G:$G),"")) | K19: Confirmed
A20: INV-0001 | B20: 9876543210 | C20: =IF($B20="","",IFERROR(_xlfn.XLOOKUP($B20,Members!$C:$C,Members!$A:$A),"NOT FOUND")) -> NOT FOUND | D20: =IF($B20="","",IFERROR(_xlfn.XLOOKUP($B20,Members!$C:$C,Members!$B:$B),"NOT FOUND")) -> NOT FOUND | E20: 45292 | F20: 2000000 | G20: Sample project — replace | H20: =IF(OR($B20="",$F20=""),"",$F20*IFERROR(IF(AND(_xlfn.XLOOKUP($B20,Members!$C:$C,Members!$H:$H)<>"",ISNUMBER(_xlfn.XLOOKUP($B20,Members!$C:$C,Members!$H:$H))),_xlfn.XLOOKUP($B20,Members!$C:$C,Members!$H:$H),IF(ISNUMBER(SEARCH("Diamond",J20)),Settings!$D$10,IF(ISNUMBER(SEARCH("Platinum",J20)),Settings!$C$10,Settings!$B$10))),0)) -> 0 | I20: =IF(OR($F20="",$H20=""),"",$F20-$H20) -> 2000000 | J20: =IF($B20="","",IFERROR(_xlfn.XLOOKUP($B20,Members!$C:$C,Members!$G:$G),"")) | K20: Confirmed
A21: INV-0001 | B21: 9876543210 | C21: =IF($B21="","",IFERROR(_xlfn.XLOOKUP($B21,Members!$C:$C,Members!$A:$A),"NOT FOUND")) -> NOT FOUND | D21: =IF($B21="","",IFERROR(_xlfn.XLOOKUP($B21,Members!$C:$C,Members!$B:$B),"NOT FOUND")) -> NOT FOUND | E21: 45292 | F21: 2000000 | G21: Sample project — replace | H21: =IF(OR($B21="",$F21=""),"",$F21*IFERROR(IF(AND(_xlfn.XLOOKUP($B21,Members!$C:$C,Members!$H:$H)<>"",ISNUMBER(_xlfn.XLOOKUP($B21,Members!$C:$C,Members!$H:$H))),_xlfn.XLOOKUP($B21,Members!$C:$C,Members!$H:$H),IF(ISNUMBER(SEARCH("Diamond",J21)),Settings!$D$10,IF(ISNUMBER(SEARCH("Platinum",J21)),Settings!$C$10,Settings!$B$10))),0)) -> 0 | I21: =IF(OR($F21="",$H21=""),"",$F21-$H21) -> 2000000 | J21: =IF($B21="","",IFERROR(_xlfn.XLOOKUP($B21,Members!$C:$C,Members!$G:$G),"")) | K21: Confirmed
A22: INV-0001 | B22: 9876543210 | C22: =IF($B22="","",IFERROR(_xlfn.XLOOKUP($B22,Members!$C:$C,Members!$A:$A),"NOT FOUND")) -> NOT FOUND | D22: =IF($B22="","",IFERROR(_xlfn.XLOOKUP($B22,Members!$C:$C,Members!$B:$B),"NOT FOUND")) -> NOT FOUND | E22: 45292 | F22: 2000000 | G22: Sample project — replace | H22: =IF(OR($B22="",$F22=""),"",$F22*IFERROR(IF(AND(_xlfn.XLOOKUP($B22,Members!$C:$C,Members!$H:$H)<>"",ISNUMBER(_xlfn.XLOOKUP($B22,Members!$C:$C,Members!$H:$H))),_xlfn.XLOOKUP($B22,Members!$C:$C,Members!$H:$H),IF(ISNUMBER(SEARCH("Diamond",J22)),Settings!$D$10,IF(ISNUMBER(SEARCH("Platinum",J22)),Settings!$C$10,Settings!$B$10))),0)) -> 0 | I22: =IF(OR($F22="",$H22=""),"",$F22-$H22) -> 2000000 | J22: =IF($B22="","",IFERROR(_xlfn.XLOOKUP($B22,Members!$C:$C,Members!$G:$G),"")) | K22: Confirmed
... A55: INV-0001 | B55: 9876543210 | C55: =IF($B55="","",IFERROR(_xlfn.XLOOKUP($B55,Members!$C:$C,Members!$A:$A),"NOT FOUND")) -> NOT FOUND | D55: =IF($B55="","",IFERROR(_xlfn.XLOOKUP($B55,Members!$C:$C,Members!$B:$B),"NOT FOUND")) -> NOT FOUND | E55: 45292 | F55: 2000000 | G55: Sample project — replace | H55: =IF(OR($B55="",$F55=""),"",$F55*IFERROR(IF(AND(_xlfn.XLOOKUP($B55,Members!$C:$C,Members!$H:$H)<>"",ISNUMBER(_xlfn.XLOOKUP($B55,Members!$C:$C,Members!$H:$H))),_xlfn.XLOOKUP($B55,Members!$C:$C,Members!$H:$H),IF(ISNUMBER(SEARCH("Diamond",J55)),Settings!$D$10,IF(ISNUMBER(SEARCH("Platinum",J55)),Settings!$C$10,Settings!$B$10))),0)) -> 0 | I55: =IF(OR($F55="",$H55=""),"",$F55-$H55) -> 2000000 | J55: =IF($B55="","",IFERROR(_xlfn.XLOOKUP($B55,Members!$C:$C,Members!$G:$G),"")) | K55: Confirmed
A56: TOTALS | F56: =SUMIFS(F6:F55,K6:K55,"Confirmed") -> 101000000 | H56: =SUMIFS(H6:H55,K6:K55,"Confirmed") -> 700000 | I56: =SUMIFS(I6:I55,K6:K55,"Confirmed") -> 100300000
